aioplemmy/__init__.py
aioplemmy/lemmyhttp.py
aioplemmy/objects.py
aioplemmy/responses.py
aioplemmy/version.py
aioplemmy/views.py
aioplemmy-0.3.3.dist-info/LICENSE
aioplemmy-0.3.3.dist-info/METADATA
aioplemmy-0.3.3.dist-info/WHEEL
aioplemmy-0.3.3.dist-info/top_level.txt
aioplemmy-0.3.3.dist-info/RECORD
