Metadata-Version: 2.1
Name: aioplemmy
Version: 0.3.3
Summary: Python API for LemmyHttp
Home-page: https://github.com/schicksal-hq/plemmy
Author: Travis Kessler
Author-email: travis.j.kessler@gmail.com
License: Apache License 2.0
License-File: LICENSE
Requires-Dist: orjson (==3.9.2)
Requires-Dist: aiohttp (==3.8.5)
